labgraph_cpp.cpython-38-x86_64-linux-gnu.so
cthulhubindings.cpython-38-x86_64-linux-gnu.so
MyCPPNodes.cpython-38-x86_64-linux-gnu.so
labgraph-2.0.1.dist-info/METADATA
labgraph-2.0.1.dist-info/WHEEL
labgraph-2.0.1.dist-info/top_level.txt
labgraph-2.0.1.dist-info/RECORD
backup_labgraph/__init__.py
backup_labgraph/simulations/function_generator.py
backup_labgraph/simulations/__init__.py
backup_labgraph/simulations/function_generator_node.py
backup_labgraph/loggers/logger.py
backup_labgraph/loggers/__init__.py
backup_labgraph/loggers/tests/test_loggers.py
backup_labgraph/loggers/tests/__init__.py
backup_labgraph/loggers/hdf5/logger.py
backup_labgraph/loggers/hdf5/__init__.py
backup_labgraph/tests/test_imports.py
backup_labgraph/tests/test_typecheck.py
backup_labgraph/tests/__init__.py
backup_labgraph/cpp/__init__.py
backup_labgraph/examples/bandpass_viz.py
backup_labgraph/examples/simple_viz.py
backup_labgraph/examples/__init__.py
backup_labgraph/examples/simulation.py
backup_labgraph/graphs/stream.py
backup_labgraph/graphs/module.py
backup_labgraph/graphs/state.py
backup_labgraph/graphs/graph.py
backup_labgraph/graphs/group.py
backup_labgraph/graphs/node.py
backup_labgraph/graphs/node_test_harness.py
backup_labgraph/graphs/config.py
backup_labgraph/graphs/method.py
backup_labgraph/graphs/cpp_node.py
backup_labgraph/graphs/parent_graph_info.py
backup_labgraph/graphs/__init__.py
backup_labgraph/graphs/topic.py
backup_labgraph/graphs/tests/test_graph.py
backup_labgraph/graphs/tests/test_harness.py
backup_labgraph/graphs/tests/test_module.py
backup_labgraph/graphs/tests/test_config.py
backup_labgraph/graphs/tests/test_publisher.py
backup_labgraph/graphs/tests/test_subscriber.py
backup_labgraph/graphs/tests/test_group.py
backup_labgraph/graphs/tests/test_node.py
backup_labgraph/graphs/tests/__init__.py
backup_labgraph/messages/message.py
backup_labgraph/messages/types.py
backup_labgraph/messages/__init__.py
backup_labgraph/messages/tests/test_message.py
backup_labgraph/messages/tests/__init__.py
backup_labgraph/util/typing.py
backup_labgraph/util/logger.py
